LoveCalculator/Calculator.py
LoveCalculator/__init__.py
LoveCalculator-0.1.1.dist-info/LICENSE
LoveCalculator-0.1.1.dist-info/METADATA
LoveCalculator-0.1.1.dist-info/WHEEL
LoveCalculator-0.1.1.dist-info/top_level.txt
LoveCalculator-0.1.1.dist-info/RECORD
