Metadata-Version: 2.1
Name: LoveCalculator
Version: 0.1.1
Summary: An enchanting Python module designed to ignite the flames of affection! Dive into the realm of romance as PyLoveCalc seamlessly computes couple names and unveils the mystical percentage of love that binds them together.
License-File: LICENSE
